coingeckoprice/__init__.py
coingeckoprice/coingeckoprice.py
coingecko_price-0.0.2.dist-info/LICENSE
coingecko_price-0.0.2.dist-info/METADATA
coingecko_price-0.0.2.dist-info/WHEEL
coingecko_price-0.0.2.dist-info/top_level.txt
coingecko_price-0.0.2.dist-info/RECORD
